Workbook

Sheet Dashboard
A1: Budget Dashboard v2
A3: Current Month | B3: =TEXT(TODAY(),"yyyy-mm")
A4: Total Income (actual) | B4: =SUM(Income!D2:D200)
A5: Total Expenses | B5: =SUMIFS(Transactions!C2:C301,Transactions!D2:D301,"Expense")
A6: Net Balance | B6: =B4-B5
A7: Starting Balance | B7: =Setup!B6
A8: Available Balance | B8: =B7+B6
A10: Savings Goals
A11: Goal | B11: Target | C11: Saved | D11: Remaining
A12: =IF(Savings_Goals!A2="","",Savings_Goals!A2) | B12: =IF(Savings_Goals!B2="","",Savings_Goals!B2) | C12: =IF(Savings_Goals!C2="","",Savings_Goals!C2) | D12: =IF(B12="","",B12-C12)
A13: =IF(Savings_Goals!A3="","",Savings_Goals!A3) | B13: =IF(Savings_Goals!B3="","",Savings_Goals!B3) | C13: =IF(Savings_Goals!C3="","",Savings_Goals!C3) | D13: =IF(B13="","",B13-C13)
A14: =IF(Savings_Goals!A4="","",Savings_Goals!A4) | B14: =IF(Savings_Goals!B4="","",Savings_Goals!B4) | C14: =IF(Savings_Goals!C4="","",Savings_Goals!C4) | D14: =IF(B14="","",B14-C14)
A15: =IF(Savings_Goals!A5="","",Savings_Goals!A5) | B15: =IF(Savings_Goals!B5="","",Savings_Goals!B5) | C15: =IF(Savings_Goals!C5="","",Savings_Goals!C5) | D15: =IF(B15="","",B15-C15)
A16: =IF(Savings_Goals!A6="","",Savings_Goals!A6) | B16: =IF(Savings_Goals!B6="","",Savings_Goals!B6) | C16: =IF(Savings_Goals!C6="","",Savings_Goals!C6) | D16: =IF(B16="","",B16-C16)
A17: =IF(Savings_Goals!A7="","",Savings_Goals!A7) | B17: =IF(Savings_Goals!B7="","",Savings_Goals!B7) | C17: =IF(Savings_Goals!C7="","",Savings_Goals!C7) | D17: =IF(B17="","",B17-C17)
A18: =IF(Savings_Goals!A8="","",Savings_Goals!A8) | B18: =IF(Savings_Goals!B8="","",Savings_Goals!B8) | C18: =IF(Savings_Goals!C8="","",Savings_Goals!C8) | D18: =IF(B18="","",B18-C18)
A19: =IF(Savings_Goals!A9="","",Savings_Goals!A9) | B19: =IF(Savings_Goals!B9="","",Savings_Goals!B9) | C19: =IF(Savings_Goals!C9="","",Savings_Goals!C9) | D19: =IF(B19="","",B19-C19)
A20: =IF(Savings_Goals!A10="","",Savings_Goals!A10) | B20: =IF(Savings_Goals!B10="","",Savings_Goals!B10) | C20: =IF(Savings_Goals!C10="","",Savings_Goals!C10) | D20: =IF(B20="","",B20-C20)
A21: =IF(Savings_Goals!A11="","",Savings_Goals!A11) | B21: =IF(Savings_Goals!B11="","",Savings_Goals!B11) | C21: =IF(Savings_Goals!C11="","",Savings_Goals!C11) | D21: =IF(B21="","",B21-C21)
A22: =IF(Savings_Goals!A12="","",Savings_Goals!A12) | B22: =IF(Savings_Goals!B12="","",Savings_Goals!B12) | C22: =IF(Savings_Goals!C12="","",Savings_Goals!C12) | D22: =IF(B22="","",B22-C22)
A23: =IF(Savings_Goals!A13="","",Savings_Goals!A13) | B23: =IF(Savings_Goals!B13="","",Savings_Goals!B13) | C23: =IF(Savings_Goals!C13="","",Savings_Goals!C13) | D23: =IF(B23="","",B23-C23)
... A29: =IF(Savings_Goals!A19="","",Savings_Goals!A19) | B29: =IF(Savings_Goals!B19="","",Savings_Goals!B19) | C29: =IF(Savings_Goals!C19="","",Savings_Goals!C19) | D29: =IF(B29="","",B29-C29)

Sheet Transactions
A1: Date | B1: Category | C1: Amount | D1: Type | E1: Description | F1: Payment Method | G1: Status | H1: Month | I1: Week | J1: Notes
H2: =IF(A2="","",TEXT(A2,"yyyy-mm")) | I2: =IF(A2="","",WEEKNUM(A2,2))
H3: =IF(A3="","",TEXT(A3,"yyyy-mm")) | I3: =IF(A3="","",WEEKNUM(A3,2))
H4: =IF(A4="","",TEXT(A4,"yyyy-mm")) | I4: =IF(A4="","",WEEKNUM(A4,2))
H5: =IF(A5="","",TEXT(A5,"yyyy-mm")) | I5: =IF(A5="","",WEEKNUM(A5,2))
H6: =IF(A6="","",TEXT(A6,"yyyy-mm")) | I6: =IF(A6="","",WEEKNUM(A6,2))
H7: =IF(A7="","",TEXT(A7,"yyyy-mm")) | I7: =IF(A7="","",WEEKNUM(A7,2))
H8: =IF(A8="","",TEXT(A8,"yyyy-mm")) | I8: =IF(A8="","",WEEKNUM(A8,2))
H9: =IF(A9="","",TEXT(A9,"yyyy-mm")) | I9: =IF(A9="","",WEEKNUM(A9,2))
H10: =IF(A10="","",TEXT(A10,"yyyy-mm")) | I10: =IF(A10="","",WEEKNUM(A10,2))
H11: =IF(A11="","",TEXT(A11,"yyyy-mm")) | I11: =IF(A11="","",WEEKNUM(A11,2))
H12: =IF(A12="","",TEXT(A12,"yyyy-mm")) | I12: =IF(A12="","",WEEKNUM(A12,2))
H13: =IF(A13="","",TEXT(A13,"yyyy-mm")) | I13: =IF(A13="","",WEEKNUM(A13,2))
... H301: =IF(A301="","",TEXT(A301,"yyyy-mm")) | I301: =IF(A301="","",WEEKNUM(A301,2))

Sheet Recurring
A1: Active | B1: Start Date | C1: End Date | D1: Category | E1: Projected Amount | F1: Frequency | G1: Description | H1: Type
A2: TRUE | B2: 46023 | D2: Bills | E2: 40.25 | F2: Monthly | G2: Internet Phone | H2: Expense
A3: TRUE | B3: 46023 | D3: Bills | E3: 14.94 | F3: Monthly | G3: Disney Plus | H3: Expense
A4: TRUE | B4: 46023 | D4: Bills | E4: 5.74 | F4: Monthly | G4: Amazon Prime | H4: Expense
A5: TRUE | B5: 46023 | D5: Bills | E5: 6.87 | F5: Monthly | G5: Apple Music | H5: Expense

Sheet Income
A1: Date | B1: Source | C1: Projected Amount | D1: Actual Amount | E1: Status | F1: Notes
A2: 46030 | B2: Paycheck 1 | C2: 820 | E2: Planned
A3: 46044 | B3: Paycheck 2 | C3: 820 | E3: Planned

Sheet Savings_Goals
A1: Goal | B1: Target Amount | C1: Current Saved | D1: Monthly Target | E1: Priority | F1: Target Date | G1: Status
A2: Emergency Fund | B2: 3000 | C2: 0 | D2: 200 | E2: High | F2: 46387 | G2: Active
A3: Holiday | B3: 1500 | C3: 0 | D3: 100 | E3: Medium | F3: 46266 | G3: Active

Sheet Categories
A1: Category | B1: Type | C1: Priority | D1: Description
A2: Groceries | B2: Expense | C2: High | D2: Food and essentials
A3: Transport | B3: Expense | C3: High | D3: Transit, gas, parking
A4: Eating Out | B4: Expense | C4: Medium | D4: Restaurants and delivery
A5: Shopping | B5: Expense | C5: Low | D5: Clothes and discretionary
A6: Bills | B6: Expense | C6: High | D6: Rent, phone, internet, subscriptions
A7: Health | B7: Expense | C7: High | D7: Physical and mental wellbeing
A8: Business | B8: Expense | C8: Medium | D8: Business and projects
A9: Family/Friends | B9: Expense | C9: Medium | D9: Social and family spending
A10: Income - Paycheck | B10: Income | C10: High | D10: Regular paycheck
A11: Income - Other | B11: Income | C11: Medium | D11: Other incoming money
A12: Emergency Fund | B12: Saving | C12: High | D12: Emergency reserve
A13: Holiday | B13: Saving | C13: Medium | D13: Travel and holidays

Sheet Setup
A1: Parameter | B1: Value | C1: Notes
A2: Budget Owner | B2: Hassan | C2: Editable
A3: Default Currency | B3: CAD | C3: Editable
A4: Budget Start Date | B4: 46023 | C4: Editable
A5: Pay Cycle Days | B5: 14 | C5: Editable
A6: Starting Balance | B6: 0 | C6: Editable
